{
    "general": {
        "dashboardName": "General",
        "translationKey": "DASHBOARD_TAB_GENERAL_KEY",
        "displayByDefault": true,
        "maxRecentlyViewedPatients": 10,
        "sections": {
            "patientInformation": {
                "title": "Patient Information",
                "name": "patientInformation",
                "translationKey": "DASHBOARD_TITLE_PATIENT_INFORMATION_KEY",
                "type": "patientInformation",
                "displayOrder": 0,
                "ageLimit":100,
                "patientAttributes": ["occupation"],
                "addressFields": [
                    "address1",
                    "address2",
                    "cityVillage",
                    "countryDistrict"
                ]
            },
            "diagnosis": {
                "title": "Diagnosis",
                "name": "diagnosis",
                "showCertainty": true,
                "showOrder": true,
                "displayOrder": 1
            },

            "disposition": {
                "title": "Disposition",
                "name": "disposition",
                "numberOfVisits": 1,
                "displayOrder": 2
            },
            "treatments": {
                "title": "Treatments",
                "name": "treatment",
                "displayOrder": 3,
                "dashboardParams": {
                    "showFlowSheet": true,
                    "showListView": true,
                    "showRoute": true,
                    "showDrugForm": true,
                    "numberOfVisits": 5,
                    "showOtherActive": true,
                    "showDetailsButton": true
                },
                "allTreatmentDetails": {
                    "title": "Treatments",
                    "showFlowSheet": true,
                    "showListView": true,
                    "showRoute": true,
                    "showDrugForm": true,
                    "numberOfVisits": 10,
                    "showOtherActive": true,
                    "showDetailsButton": true
                }
            },
            "programs": {
                "title": "Programs",
                "name": "programs",
                "displayOrder": 5
            },
            "navigationLinksControl": {
                "title":"Navigation Links Control",
                "translationKey": "DASHBOARD_TITLE_NAVIGATION_LINKS_CONTROL_KEY",
                "type": "navigationLinksControl",
                "displayOrder": 2,
                "links": [
                    {
                        "translationKey":"HOME_DASHBOARD_KEY",
                        "url": "../home/#/dashboard"
                    },
                    {
                        "url": "../clinical/#/default/patient/{{patientUuid}}/dashboard/visit/{{visitUuid}}/?encounterUuid=active",
                        "translationKey":"PATIENT_VISIT_PAGE_KEY"
                    },
                    {
                        "translationKey":"PATIENT_ADT_PAGE_KEY",
                        "url": "../adt/#/patient/{{patientUuid}}/visit/{{visitUuid}}/"
                    },
                    {
                        "translationKey":"PATIENT_DASHBOARD_KEY",
                        "url": "../clinical/#/default/patient/{{patientUuid}}/dashboard"
                    },
                    {
                        "translationKey":"PROGRAM_MANAGEMENT_PAGE_KEY",
                        "url": "../clinical/#/programs/patient/{{patientUuid}}/consultationContext"
                    },
                    {
                        "translationKey":"CONSULTATION_PAGE_KEY",

                        "url": "../clinical/#/default/patient/{{patientUuid}}/concept-set-group/observations"
                    }
                ]
            },
            "vitals": {
                "title": "Vitals",
                "name": "vitals",
                "isObservation": true,
                "displayOrder": 12,
                "dashboardParams": {
                    "conceptNames": [
                        "Vitals"
                    ],
                    "numberOfVisits": 2
                },
                "allObservationDetails": {
                    "conceptNames": [
                        "Vitals"
                    ],
                    "numberOfVisits": 2,
                    "showDetailsButton": true,
                    "pivotTable": {
                        "numberOfVisits": "10",
                        "groupBy": "encounters",
                        "obsConcepts": [
                            "Weight",
                            "Vitals"
                        ],
                        "drugConcepts": [],
                        "labConcepts": []
                    }
                }
            },
            "secondVitals": {
                "title": "Second Vitals",
                "name": "second vitals",
                "isObservation": true,
                "displayOrder": 13,
                "dashboardParams": {
                    "conceptNames": [
                        "Second Vitals"
                    ],
                    "numberOfVisits": 2
                },
                "allObservationDetails": {
                    "conceptNames": [
                        "Second Vitals"
                    ],
                    "numberOfVisits": 2,
                    "showDetailsButton": true,
                    "pivotTable": {}
                }
            },
            "historyAndExaminations": {
                "title": "History and Examinations",
                "name": "vitals",
                "isObservation": true,
                "displayOrder": 14,
                "dashboardParams": {
                    "conceptNames": [
                        "History and Examination"
                    ],
                    "numberOfVisits": 2
                },
                "allObservationDetails": {
                    "conceptNames": [
                        "History and Examination"
                    ],
                    "numberOfVisits": 2,
                    "showDetailsButton": true,
                    "pivotTable": {}
                }
            },
            "gynaecology": {
                "title": "Gynaecology",
                "name": "gynaecology",
                "isObservation": true,
                "displayOrder": 15,
                "dashboardParams": {
                    "conceptNames": [
                        "Gynaecology"
                    ],
                    "numberOfVisits": 2
                },
                "allObservationDetails": {
                    "conceptNames": [
                        "Gynaecology"
                    ],
                    "numberOfVisits": 2,
                    "showDetailsButton": true,
                    "pivotTable": {}
                }
            },
            "obstetrics": {
                "title": "Obstetrics",
                "name": "obstetrics",
                "isObservation": true,
                "displayOrder": 16,
                "dashboardParams": {
                    "conceptNames": [
                        "Obstetrics"
                    ],
                    "numberOfVisits": 2
                },
                "allObservationDetails": {
                    "conceptNames": [
                        "Obstetrics"
                    ],
                    "numberOfVisits": 2,
                    "showDetailsButton": true,
                    "pivotTable": {}
                }
            },
            "visits": {
                "title": "Visits",
                "name": "visits",
                "displayOrder": 1,
                "dashboardParams": {
                    "title": null,
                    "maximumNoOfVisits": 10
                }
            },
            "diabetes": {
                "title": "Diabetes",
                "templateName": "Diabetes Template",
                "name": "diseaseTemplate",
                "displayOrder": 18,
                "dashboardParams": {
                    "showOnly": []
                },
                "allDiseaseDetails": {
                    "showDetailsButton": true,
                    "pivotTable": {
                        "numberOfVisits": "15",
                        "groupBy": "encounters",
                        "obsConcepts": [
                            "Weight",
                            "Height",
                            "Systolic",
                            "Diastolic",
                            "Diabetes, Foot Exam",
                            "Diabetes, Eye Exam"
                        ],
                        "drugConcepts": [
                            "Ipratropium Pressurised",
                            "Garbhpal Rasa"
                        ],
                        "labConcepts": [
                            "RBS",
                            "FBS",
                            "PP2BS",
                            "Hb1AC",
                            "Creatinine",
                            "Albumin",
                            "Polymorph"
                        ]
                    }
                }
            }
        }
    },
    "trends": {
        "dashboardName": "Trends",
        "maxRecentlyViewedPatients": 10,
        "sections": {
            "patientInformation": {
                "title": "Patient Information",
                "name": "patientInformation",
                "patientAttributes": [
                    "caste",
                    "class",
                    "education",
                    "occupation",
                    "debt",
                    "distanceFromCenter",
                    "isUrban",
                    "cluster",
                    "RationCard",
                    "familyIncome"
                ],
                "addressFields": [
                    "address1",
                    "address2",
                    "cityVillage",
                    "countryDistrict"
                ],
                "displayOrder": 0
            },
            "growthChart": {
                "type": "observationGraph",
                "name": "observationGraph",
                "title": "Growth Chart",
                "config": {
                    "yAxisConcepts": [
                        "Weight"
                    ],
                    "referenceData": "growthChartReference.csv",
                    "numberOfVisits": 20
                },
                "displayOrder": 1
            },
            "BP": {
                "type": "observationGraph",
                "name": "observationGraph",
                "title": "BP",
                "config": {
                    "yAxisConcepts": [
                        "Systolic",
                        "Diastolic"
                    ],
                    "xAxisConcept": "observationDateTime",
                    "numberOfVisits": 10
                },
                "displayOrder": 2
            },
            "weight/BMI": {
                "type": "observationGraph",
                "name": "observationGraph",
                "title": "Weight/BMI",
                "config": {
                    "yAxisConcepts": [
                        "Weight",
                        "BMI"
                    ],
                    "xAxisConcept": "observationDateTime",
                    "numberOfVisits": 10
                },
                "displayOrder": 3
            },
            "diabetes/BloodSugar": {
                "type": "observationGraph",
                "name": "observationGraph",
                "title": "Diabetes/Blood Sugar",
                "config": {
                    "yAxisConcepts": [
                        "Blood Sugar Fasting",
                        "Blood Sugar P.P"
                    ],
                    "xAxisConcept": "observationDateTime",
                    "numberOfVisits": 10
                },
                "displayOrder": 4
            },
            "observationGraph": {
                "type": "observationGraph",
                "name": "observationGraph",
                "title": "Pulse",
                "config": {
                    "yAxisConcepts": [
                        "Pulse"
                    ],
                    "xAxisConcept": "observationDateTime",
                    "numberOfVisits": 10
                },
                "displayOrder": 5
            },
            "diabetes": {
                "title": "Diabetes",
                "templateName": "Diabetes, Progress",
                "name": "diseaseTemplate",
                "dashboardParams": {
                    "showOnly": []
                },
                "allDiseaseDetails": {
                    "showDetailsButton": true,
                    "pivotTable": {
                        "numberOfVisits": "10",
                        "groupBy": "visits",
                        "obsConcepts": [
                            "Diabetes, Blood Pressure",
                            "Diabetes, A1C",
                            "Diabetes, LDL",
                            "Diabetes, Ulcers on Feet",
                            "Blood Sugar Fasting",
                            "Blood Sugar PP"
                        ],
                        "labConcepts": [
                            "RBS",
                            "FBS",
                            "PP2BS",
                            "Hb1AC",
                            "Creatinine",
                            "Cholesterol"
                        ]
                    }
                },
                "displayOrder": 6
            }
        }
    }
}